mp4svg/__init__.py
mp4svg/api_server.py
mp4svg/base.py
mp4svg/cli.py
mp4svg/converters/__init__.py
mp4svg/converters/ascii85_converter.py
mp4svg/converters/hybrid_converter.py
mp4svg/converters/polyglot_converter.py
mp4svg/converters/qrcode_converter.py
mp4svg/converters/vector_converter.py
mp4svg/grpc_client.py
mp4svg/grpc_server.py
mp4svg/mcp_client.py
mp4svg/mcp_server.py
mp4svg/mp4svg.proto
mp4svg/shell.py
mp4svg/validators/__init__.py
mp4svg/validators/integrity_validator.py
mp4svg/validators/svg_validator.py
mp4svg-1.0.10.dist-info/LICENSE
mp4svg-1.0.10.dist-info/METADATA
mp4svg-1.0.10.dist-info/WHEEL
mp4svg-1.0.10.dist-info/entry_points.txt
mp4svg-1.0.10.dist-info/RECORD
