Metadata-Version: 2.3
Name: mp4svg
Version: 1.0.10
Summary: Convert MP4 videos to SVG containers using multiple encoding methods
Keywords: video,svg,conversion,ascii85,polyglot
Author: Tom Sapletta
Author-email: info@softreck.dev
Requires-Python: >=3.8.1
Classifier: Development Status :: 4 - Beta
Classifier: Intended Audience :: Developers
Classifier: Intended Audience :: End Users/Desktop
Classifier: License :: OSI Approved :: MIT License
Classifier: Operating System :: OS Independent
Classifier: Programming Language :: Python :: 3
Classifier: Programming Language :: Python :: 3.9
Classifier: Programming Language :: Python :: 3.10
Classifier: Programming Language :: Python :: 3.11
Classifier: Programming Language :: Python :: 3.12
Classifier: Programming Language :: Python :: 3.13
Classifier: Programming Language :: Python :: 3.8
Classifier: Topic :: Multimedia :: Video :: Conversion
Classifier: Topic :: Software Development :: Libraries :: Python Modules
Classifier: Topic :: Utilities
Requires-Dist: Pillow (>=10.0.0,<11.0.0)
Requires-Dist: fastapi (>=0.104.0,<0.105.0)
Requires-Dist: grpcio (>=1.60.0,<2.0.0)
Requires-Dist: grpcio-tools (>=1.60.0,<2.0.0)
Requires-Dist: lxml (>=4.9.0,<5.0.0)
Requires-Dist: mcp (>=1.0.0,<2.0.0)
Requires-Dist: mcp-client (>=1.0.0,<2.0.0)
Requires-Dist: numpy (>=1.24.0,<2.0.0)
Requires-Dist: opencv-python (>=4.8.0,<5.0.0)
Requires-Dist: protobuf (>=4.25.0,<5.0.0)
Requires-Dist: pydantic (>=2.5.0,<3.0.0)
Requires-Dist: python-multipart (>=0.0.6,<0.0.7)
Requires-Dist: qrcode (>=7.4.0,<8.0.0)
Requires-Dist: uvicorn (>=0.24.0,<0.25.0)
Project-URL: Documentation, https://mp4svg.readthedocs.io
Project-URL: Homepage, https://github.com/veridock/mp4svg
Project-URL: Repository, https://github.com/veridock/mp4svg
